__init__.py
dirigera/__init__.py
dirigera/devices/__init__.py
dirigera/devices/air_purifier.py
dirigera/devices/base_ikea_model.py
dirigera/devices/blinds.py
dirigera/devices/controller.py
dirigera/devices/device.py
dirigera/devices/environment_sensor.py
dirigera/devices/light.py
dirigera/devices/light_sensor.py
dirigera/devices/motion_sensor.py
dirigera/devices/occupancy_sensor.py
dirigera/devices/open_close_sensor.py
dirigera/devices/outlet.py
dirigera/devices/scene.py
dirigera/devices/water_sensor.py
dirigera/hub/__init__.py
dirigera/hub/abstract_smart_home_hub.py
dirigera/hub/auth.py
dirigera/hub/hub.py
dirigera/hub/utils.py
dirigera-1.2.5.dist-info/licenses/LICENSE
dirigera-1.2.5.dist-info/METADATA
dirigera-1.2.5.dist-info/WHEEL
dirigera-1.2.5.dist-info/entry_points.txt
dirigera-1.2.5.dist-info/top_level.txt
dirigera-1.2.5.dist-info/RECORD
