Metadata-Version: 2.4
Name: dirigera
Version: 1.2.5
Summary: An unofficial Python client for controlling the IKEA Dirigera Smart Home Hub
Author-email: Leggin <legginsun@gmail.com>
License: MIT License
Project-URL: Homepage, https://github.com/Leggin/dirigera
Keywords: python,iot,smarthome,hub,lighting,ikea,tradfri,dirigera
Classifier: Programming Language :: Python :: 3.7
Classifier: Programming Language :: Python :: 3.8
Classifier: Programming Language :: Python :: 3.9
Classifier: Programming Language :: Python :: 3.10
Classifier: Programming Language :: Python :: 3.11
Classifier: Programming Language :: Python :: 3.12
Classifier: License :: OSI Approved :: MIT License
Classifier: Operating System :: OS Independent
Requires-Python: >=3.7
License-File: LICENSE
Requires-Dist: requests>=2.22.0
Requires-Dist: websocket-client>=1.0.0
Requires-Dist: pydantic>=1.10.0
Provides-Extra: dev
Requires-Dist: black; extra == "dev"
Requires-Dist: pytest; extra == "dev"
Dynamic: license-file
